LICENSE
README.rst
setup.py
examples/deep_fake/__init__.py
examples/deep_fake/src/__init__.py
examples/deep_fake/src/data_loading.py
examples/deep_fake/src/deep_models.py
examples/deep_fake/src/util.py
omnifig/__init__.py
omnifig/_info.py
omnifig/abstract.py
omnifig/configurable.py
omnifig/exporting.py
omnifig/mixins.py
omnifig/registration.py
omnifig/top.py
omnifig.egg-info/PKG-INFO
omnifig.egg-info/SOURCES.txt
omnifig.egg-info/dependency_links.txt
omnifig.egg-info/entry_points.txt
omnifig.egg-info/not-zip-safe
omnifig.egg-info/requires.txt
omnifig.egg-info/top_level.txt
omnifig/behaviors/__init__.py
omnifig/behaviors/base.py
omnifig/behaviors/debug.py
omnifig/behaviors/help.py
omnifig/behaviors/quiet.py
omnifig/config/__init__.py
omnifig/config/abstract.py
omnifig/config/manager.py
omnifig/config/nodes.py
omnifig/organization/__init__.py
omnifig/organization/default.py
omnifig/organization/profiles.py
omnifig/organization/workspaces.py
tests/test_config.py
tests/test_configurable.py
tests/test_projects.py
tests/test_running.py
tests/test_running_behaviors.py