Metadata-Version: 2.4
Name: omnifig
Version: 1.0.10
Summary: Unleashing Project Configuration and Organization
Home-page: https://github.com/felixludos/omni-fig
Author: Felix Leeb
Author-email: felixludos@hotmail.com
License: MIT
License-File: LICENSE
Requires-Dist: omnibelt>=0.8.8
Requires-Dist: pyyaml
Requires-Dist: toml
Requires-Dist: tabulate
Dynamic: author
Dynamic: author-email
Dynamic: home-page
Dynamic: license
Dynamic: license-file
Dynamic: requires-dist
Dynamic: summary
